product_release_notes/__init__.py
product_release_notes/admin.py
product_release_notes/apps.py
product_release_notes/feed.py
product_release_notes/google_play.py
product_release_notes/itunes.py
product_release_notes/models.py
product_release_notes/tests.py
product_release_notes/urls.py
product_release_notes/views.py
product_release_notes/management/__init__.py
product_release_notes/management/commands/__init__.py
product_release_notes/management/commands/check_app_stores.py
product_release_notes/migrations/0001_initial.py
product_release_notes/migrations/0002_releasenote_version.py
product_release_notes/migrations/0003_client_icon.py
product_release_notes/migrations/0004_auto_20170821_2340.py
product_release_notes/migrations/0005_client_google_play_url.py
product_release_notes/migrations/0006_auto_20170905_2248.py
product_release_notes/migrations/0007_auto_20220225_1500.py
product_release_notes/migrations/__init__.py
product_release_notes/templates/release_notes/base.html
product_release_notes/templates/release_notes/list.html
product_release_notes/templatetags/__init__.py
product_release_notes/templatetags/release_notes.py
project/__init__.py
project/settings.py
project/urls.py
project/wsgi.py
product_release_notes-1.1.1.dist-info/LICENSE
product_release_notes-1.1.1.dist-info/METADATA
product_release_notes-1.1.1.dist-info/WHEEL
product_release_notes-1.1.1.dist-info/top_level.txt
product_release_notes-1.1.1.dist-info/RECORD
