Metadata-Version: 2.1
Name: product-release-notes
Version: 1.1.1
Summary: Release notes page for your product.
Home-page: https://github.com/nickromano/product-release-notes
Author: Nick Romano
Author-email: nick.r.romano@gmail.com
License: MIT
Platform: UNKNOWN
Classifier: Framework :: Django
Classifier: Intended Audience :: Developers
Classifier: License :: OSI Approved :: BSD License
Classifier: Operating System :: OS Independent
Classifier: Programming Language :: Python
Classifier: Programming Language :: Python :: 2
Classifier: Programming Language :: Python :: 2.7
Classifier: Programming Language :: Python :: 3
Classifier: Programming Language :: Python :: 3.5
License-File: LICENSE
Requires-Dist: Django (>=2.0)
Requires-Dist: beautifulsoup4
Requires-Dist: requests
Requires-Dist: markdown
Requires-Dist: six
